my_python_module/__init__.py
my_python_module/common.py
my_python_module/compat.py
my_python_module/datetime.py
my_python_module/dict.py
my_python_module/exceptions.py
my_python_module/functools.py
my_python_module/json.py
my_python_module/list.py
my_python_module/math.py
my_python_module/number.py
my_python_module/pathlib.py
my_python_module/str.py
my_python_module/unique_key.py
my_python_module/zhnumber.py
my_python_module/algorithm/__init__.py
my_python_module/algorithm/binary_search.py
my_python_module/algorithm/graph/__init__.py
my_python_module/algorithm/graph/dag.py
my_python_module/algorithm/graph/directed_graph.py
my_python_module/algorithm/graph/exceptions.py
my_python_module/algorithm/graph/graph.py
my_python_module/algorithm/graph/undirected_graph.py
my_python_module/algorithm/graph/weighted_dag.py
my_python_module/algorithm/problems/__init__.py
my_python_module/algorithm/problems/hanoi.py
my_python_module/algorithm/problems/random_walk.py
my_python_module/algorithm/sort/__init__.py
my_python_module/algorithm/sort/bubble_sort.py
my_python_module/algorithm/sort/quick_sort.py
my_python_module/algorithm/sort/select_sort.py
my_python_module/algorithm/tree/__init__.py
my_python_module/algorithm/tree/binary_decision_tree.py
my_python_module/algorithm/tree/binary_search_tree.py
my_python_module/algorithm/tree/exceptions.py
my_python_module/algorithm/tree/tree.py
my_python_module/ipynb/__init__.py
my_python_module/ipynb/linear_algebra.py
my_python_module/ipynb/nn_model.py
my_python_module/nlp/__init__.py
my_python_module/nlp/chinese_stop_words.py
my_python_module/nlp/nltk_utils.py
my_python_module/nlp/text.py
my_python_module/nlp/tokenize.py
my_python_module/nlp/utils.py
my_python_module-0.5.7.dist-info/LICENSE
my_python_module-0.5.7.dist-info/METADATA
my_python_module-0.5.7.dist-info/WHEEL
my_python_module-0.5.7.dist-info/top_level.txt
my_python_module-0.5.7.dist-info/RECORD
