Metadata-Version: 2.1
Name: my_python_module
Version: 0.5.7
Summary: a general purpose python module.
Home-page: https://github.com/a358003542/my_python_module
Author: wanze
Author-email: a358003542@outlook.com
Maintainer: wanze
Maintainer-email: a358003542@outlook.com
License: MIT
Keywords: python
Classifier: License :: OSI Approved :: MIT License
Classifier: Operating System :: Microsoft
Classifier: Operating System :: POSIX :: Linux
Classifier: Programming Language :: Python :: 3
License-File: LICENSE
